rfc9839/__init__.py
rfc9839/rfc9839.py
rfc9839-0.0.2.dist-info/licenses/LICENSE
rfc9839-0.0.2.dist-info/WHEEL
rfc9839-0.0.2.dist-info/METADATA
rfc9839-0.0.2.dist-info/RECORD
