Metadata-Version: 2.4
Name: rfc9839
Version: 0.0.2
Summary: Python library to check for problematic Unicode code points.
Keywords: unicode,rfc9839,surrogates,control codes,noncharacters,unicode scalars,xml characters,unicode assignables,security
Author: Wu Tingfeng
Author-email: Wu Tingfeng <wutingfeng@outlook.com>
License-Expression: MIT
License-File: LICENSE
Classifier: Operating System :: OS Independent
Classifier: Programming Language :: Python :: 3 :: Only
Classifier: Programming Language :: Python :: 3.9
Classifier: Programming Language :: Python :: 3.10
Classifier: Programming Language :: Python :: 3.11
Classifier: Programming Language :: Python :: 3.12
Classifier: Programming Language :: Python :: 3.13
Classifier: Programming Language :: Python :: 3.14
Requires-Python: >=3.9
Project-URL: Homepage, https://github.com/elliotwutingfeng/rfc9839
Project-URL: Issues, https://github.com/elliotwutingfeng/rfc9839/issues
